Workbook

Sheet Instrucciones
A1: P&L Quest: ficha de revisión de dominio
A2: Para qué sirve | B2: Comprobar que las 48 situaciones del modo Año completo (192 respuestas) suenan reales en el negocio y que cada respuesta mueve la línea correcta del P&L. Los datos del juego son ficticios.
A3: Cuánto toma | B3: Cerca de 1 hora. Lee una fila a la vez: la escena, la respuesta y la línea que el juego dice que mueve.
A4: Hoja Revisión | B4: Una fila por respuesta. Completa las celdas amarillas: ¿Realista? (Sí, No o Ambiguo), Línea correcta (la del P&L que a tu juicio mueve la respuesta; «Fuera del P&L» si es caja, deuda, impuestos u otra cosa) y Comentario (obligatorio si marcas No, Ambiguo o una línea distinta). Las columnas en inglés son para quien revise la traducción.
A5: Hoja Problemas | B5: Una fila por situación. Dime si la escena es realista, si la respuesta equilibrada es de verdad la mejor y si falta una opción mejor.
A6: Hoja Resumen | B6: Se calcula sola con lo que completes. No hay que tocarla.
A7: Las 6 líneas | B7: Ventas: ventas antes de incentivos. Incentivos: rebates y descuentos a clientes. Costo: costo de ventas (insumos, producción, mantención). Flete: llevar el producto al cliente. Direct Chg: cargos directos al cliente, como el comodato de equipos o las visitas de servicio. SG&A: ventas, generales y administración. Debajo de la línea de SG&A el juego termina en el OI: caja, capital de trabajo, deuda, intereses e impuestos quedan fuera.
A8: Los 4 tipos de respuesta | B8: Equilibrada: la que el juego premia (mejora el OI con una contrapartida bien diseñada). Atajo: sube el OI hoy y cobra después. Ceder: cede a la voz en tensión y el OI paga. Pasiva: no hacer nada.
A9: Criterio de aprobación | B9: Al menos 90% de las 192 respuestas marcadas «Sí» en realista y ninguna línea distinta sin resolver. Lo que marques No, Ambiguo o con otra línea se corrige y se vuelve a revisar.
A10: Revisor
A11: Nombre
A12: Área (comercial, operaciones, otra)
A13: Fecha

Sheet Revisión
A1: ID | B1: Meses | C1: Voz | D1: Escena | E1: Respuesta | F1: Descripción | G1: Línea que mueve | H1: Intención del autor | I1: ¿Realista? | J1: Línea correcta | K1: Comentario | L1: Scene (EN) | M1: Answer (EN) | N1: Description (EN) | O1: ¿Traducción correcta?
A2: m01c | B2: Cualquiera | C2: CLIENTE | D2: La minera, 18% de tus ventas, pide 3% de rebate para renovar el contrato. | E2: Contrato a 2 años | F2: Ofreces 1% de rebate y subes a 2% sobre el plan para que firmen 2 años. | G2: Incentivos | H2: Equilibrada | L2: The mine, 18% of your sales, asks for a 3% rebate to renew the contract. | M2: 2-year contract | N2: You offer a 1% rebate rising to 2% above plan if they sign for 2 years.
A3: m01c | B3: Cualquiera | C3: CLIENTE | D3: La minera, 18% de tus ventas, pide 3% de rebate para renovar el contrato. | E3: Aceptar y compensar | F3: Aceptas el 3% y compensas con un alza de 2% en sus otros productos. | G3: Ventas | H3: Atajo | L3: The mine, 18% of your sales, asks for a 3% rebate to renew the contract. | M3: Accept and offset | N3: You accept the 3% and offset it with a 2% rise on their other products.
A4: m01c | B4: Cualquiera | C4: CLIENTE | D4: La minera, 18% de tus ventas, pide 3% de rebate para renovar el contrato. | E4: Ceder el 3% | F4: Otorgas el 3% sobre el contrato y cierras la renovación esta semana. | G4: Incentivos | H4: Ceder | L4: The mine, 18% of your sales, asks for a 3% rebate to renew the contract. | M4: Give the 3% | N4: You concede the 3% on the contract and seal the renewal on the spot.
A5: m01c | B5: Cualquiera | C5: CLIENTE | D5: La minera, 18% de tus ventas, pide 3% de rebate para renovar el contrato. | E5: Pedir más plazo | F5: Pides 30 días y estudias el planteo, aunque el contrato vence en 20. | G5: Ventas | H5: Pasiva | L5: The mine, 18% of your sales, asks for a 3% rebate to renew the contract. | M5: Ask for more time | N5: You ask a month to study the offer; the contract expires in 20 days.
A6: m01p | B6: 1 a 2 | C6: PLANTA | D6: Quedan 3 semanas de insumos clave y en enero entran pedidos grandes. | E6: Compra escalonada | F6: Compras en 2 lotes, el segundo a 20 días, y avisas qué pedidos son firmes. | G6: Costo | H6: Equilibrada | L6: Key inputs cover 3 weeks and big orders arrive in January. | M6: Staggered purchase | N6: You buy in 2 lots, the second 20 days out, and flag which orders are firm.
A7: m01p | B7: 1 a 2 | C7: PLANTA | D7: Quedan 3 semanas de insumos clave y en enero entran pedidos grandes. | E7: Producir al límite | F7: Pides 110% de capacidad a la planta este mes en vez de comprar caro. | G7: Costo | H7: Atajo | L7: Key inputs cover 3 weeks and big orders arrive in January. | M7: Run at the limit | N7: You ask the plant for 110% capacity in January instead of buying dear.
A8: m01p | B8: 1 a 2 | C8: PLANTA | D8: Quedan 3 semanas de insumos clave y en enero entran pedidos grandes. | E8: Compra masiva | F8: Compras 3 meses de insumos a precio spot y atiendes cualquier demanda. | G8: Costo | H8: Ceder | L8: Key inputs cover 3 weeks and big orders arrive in January. | M8: Bulk purchase | N8: You buy 3 months of inputs at spot price and cover any demand.
A9: m01p | B9: 1 a 2 | C9: PLANTA | D9: Quedan 3 semanas de insumos clave y en enero entran pedidos grandes. | E9: Posponer compra | F9: Pospones la compra a la revisión de inventario de fin de ciclo. | G9: Costo | H9: Pasiva | L9: Key inputs cover 3 weeks and big orders arrive in January. | M9: Delay the purchase | N9: You postpone buying to the inventory review at cycle end.
A10: m01e | B10: 1 a 4 | C10: ENTORNO | D10: El dólar está 7% sobre el presupuesto y 40% de tus insumos son importados. | E10: Reajuste por dólar | F10: Pactas por escrito un reajuste según el dólar y compras a plazo la mitad. | G10: Ventas | H10: Equilibrada | L10: The dollar is 7% above budget and 40% of your inputs are imported. | M10: Dollar adjustment | N10: You agree in writing a dollar-linked adjustment and buy half forward.
A11: m01e | B11: 1 a 4 | C11: ENTORNO | D11: El dólar está 7% sobre el presupuesto y 40% de tus insumos son importados. | E11: Alza de precios | F11: Aplicas un alza de 3% desde mañana, también a los contratos vigentes. | G11: Ventas | H11: Atajo | L11: The dollar is 7% above budget and 40% of your inputs are imported. | M11: Price hike | N11: You apply a 3% rise from tomorrow, existing contracts included.
A12: m01e | B12: 1 a 4 | C12: ENTORNO | D12: El dólar está 7% sobre el presupuesto y 40% de tus insumos son importados. | E12: Absorber el golpe | F12: Dejas precios y compras igual para que el margen pague el alza de 7%. | G12: Costo | H12: Ceder | L12: The dollar is 7% above budget and 40% of your inputs are imported. | M12: Absorb the hit | N12: You leave prices and purchases as they are so the margin pays the 7% rise.
A13: m01e | B13: 1 a 4 | C13: ENTORNO | D13: El dólar está 7% sobre el presupuesto y 40% de tus insumos son importados. | E13: Analizar al cierre | F13: Analizas el efecto del dólar con los números del cierre, a 3 meses. | G13: Costo | H13: Pasiva | L13: The dollar is 7% above budget and 40% of your inputs are imported. | M13: Check at close | N13: You analyze the dollar effect with the close numbers, 3 months out.
... A193: m12s | B193: 11 a 12 | C193: ESTRATEGIA | D193: Falta 1 mes para cerrar y el OI está 1 punto bajo el plan. | E193: Ver qué sale | F193: Cierras el año como viene y analizas la diferencia con el plan después. | G193: Ventas | H193: Pasiva | L193: One month before the close and OI sits 1 point below plan. | M193: See what comes | N193: You close the year as it stands and analyze the gap to plan afterwards.

Sheet Problemas
A1: ID | B1: Meses | C1: Voz | D1: Título | E1: Escena | F1: Respuesta equilibrada | G1: ¿Escena realista? | H1: ¿La equilibrada es la mejor? | I1: ¿Falta una opción mejor? ¿Cuál? | J1: Comentario
A2: m01c | B2: Cualquiera | C2: CLIENTE | D2: Renovación anual | E2: La minera, 18% de tus ventas, pide 3% de rebate para renovar el contrato. | F2: Contrato a 2 años: Ofreces 1% de rebate y subes a 2% sobre el plan para que firmen 2 años.
A3: m01p | B3: 1 a 2 | C3: PLANTA | D3: Inventario bajo | E3: Quedan 3 semanas de insumos clave y en enero entran pedidos grandes. | F3: Compra escalonada: Compras en 2 lotes, el segundo a 20 días, y avisas qué pedidos son firmes.
A4: m01e | B4: 1 a 4 | C4: ENTORNO | D4: Presupuesto y dólar | E4: El dólar está 7% sobre el presupuesto y 40% de tus insumos son importados. | F4: Reajuste por dólar: Pactas por escrito un reajuste según el dólar y compras a plazo la mitad.
A5: m01s | B5: 1 a 3 | C5: ESTRATEGIA | D5: Medir o empujar | E5: Corporativo pide 6% más de volumen; el ahorro de tus clientes sigue sin medir. | F5: Medir el ahorro: Documentas el ahorro del agua de 3 clientes y negocias después con datos.
A6: m02c | B6: Cualquiera | C6: CLIENTE | D6: Cambio de especificación | E6: Un cliente, 12% de tus ventas, pide otra especificación con 2 semanas de aviso. | F6: Prueba corta: Haces una prueba de 3 días y pides al cliente acordar una fecha realista.
A7: m02p | B7: Cualquiera | C7: PLANTA | D7: Mantención vs pedidos | E7: Toca la mantención mayor, con 4 días de línea parada, y hay pedidos urgentes. | F7: Mantención parcial: Paras media línea en turnos, con 2 semanas de plazo, y repartes lo urgente.
A8: m02e | B8: 1 a 3 | C8: ENTORNO | D8: Lluvias altiplánicas | E8: Las lluvias cortan el camino a la faena: hay 14 despachos pendientes. | F8: Ruta alterna: Tomas la ruta sur, 120 km más larga, y priorizas lo crítico.
A9: m02s | B9: Cualquiera | C9: ESTRATEGIA | D9: Pronóstico agresivo | E9: Corporativo pide subir 8% el pronóstico del año para la reunión del lunes. | F9: Pronóstico en rango: Entregas un caso base y otro optimista de +8%, ambos explicados.
A10: m03c | B10: Cualquiera | C10: CLIENTE | D10: Lote fuera de norma | E10: Un cliente reclama 40 toneladas que salieron fuera de especificación. | F10: Reponer el lote: Repones hoy las 40 toneladas y compartes el análisis para evitar otro reclamo.
A11: m03p | B11: Cualquiera | C11: PLANTA | D11: Falla y materia prima | E11: Falla una bomba de la línea 2 y quedan 5 días de una materia prima clave. | F11: Priorizar pedidos: Priorizas los críticos con lo que queda y compras la bomba a un local.
A12: m03e | B12: Cualquiera | C12: ENTORNO | D12: Reforma tributaria | E12: Se anuncia una reforma tributaria minera y 3 clientes grandes frenan compras. | F12: Ver escenarios: Conversas por cliente sus escenarios y ofreces descuento solo a pedidos firmes.
A13: m03s | B13: Cualquiera | C13: ESTRATEGIA | D13: Producto de agua | E13: Una oportunidad: un programa de ahorro de agua que 5 mineras preguntaron. | F13: Piloto acotado: Lo pruebas 3 meses en un cliente amigo y mides el efecto antes de escalar.
... A49: m12s | B49: 11 a 12 | C49: ESTRATEGIA | D49: Cierre del año | E49: Falta 1 mes para cerrar y el OI está 1 punto bajo el plan. | F49: Congelar cargos: Congelas 2 cargos vacantes y pausas capacitaciones ajenas a las ventas.

Sheet Resumen
A1: Resumen de la revisión
A3: Respuestas en la ficha | B3: =COUNTA('Revisión'!A2:A193)
A4: Respuestas revisadas (realista marcado) | B4: =COUNTA('Revisión'!I2:I193)
A5: Realista: Sí | B5: =COUNTIF('Revisión'!I2:I193,"Sí")
A6: Realista: No | B6: =COUNTIF('Revisión'!I2:I193,"No")
A7: Realista: Ambiguo | B7: =COUNTIF('Revisión'!I2:I193,"Ambiguo")
A8: % realista (Sí / total) | B8: =IF(COUNTA('Revisión'!A2:A193)=0,0,COUNTIF('Revisión'!I2:I193,"Sí")/COUNTA('Revisión'!A2:A193))
A9: Líneas distintas a la del juego | B9: =SUMPRODUCT(('Revisión'!J2:J193<>"")*('Revisión'!J2:J193<>'Revisión'!G2:G193))
A10: Traducciones marcadas «No» | B10: =COUNTIF('Revisión'!O2:O193,"No")
A11: Escenas no realistas | B11: =COUNTIF('Problemas'!G2:G49,"No")
A12: Equilibradas que no son la mejor | B12: =COUNTIF('Problemas'!H2:H49,"No")
A13: Resultado | B13: =IF(AND(B8>=0.9,B9=0),"Aprobado","Revisar")
A16: Realista por voz | B16: Respuestas | C16: Sí | D16: No | E16: Ambiguo
A17: CLIENTE | B17: =COUNTIF('Revisión'!C2:C193,"CLIENTE") | C17: =COUNTIFS('Revisión'!C2:C193,"CLIENTE",'Revisión'!I2:I193,"Sí") | D17: =COUNTIFS('Revisión'!C2:C193,"CLIENTE",'Revisión'!I2:I193,"No") | E17: =COUNTIFS('Revisión'!C2:C193,"CLIENTE",'Revisión'!I2:I193,"Ambiguo")
A18: PLANTA | B18: =COUNTIF('Revisión'!C2:C193,"PLANTA") | C18: =COUNTIFS('Revisión'!C2:C193,"PLANTA",'Revisión'!I2:I193,"Sí") | D18: =COUNTIFS('Revisión'!C2:C193,"PLANTA",'Revisión'!I2:I193,"No") | E18: =COUNTIFS('Revisión'!C2:C193,"PLANTA",'Revisión'!I2:I193,"Ambiguo")
A19: ENTORNO | B19: =COUNTIF('Revisión'!C2:C193,"ENTORNO") | C19: =COUNTIFS('Revisión'!C2:C193,"ENTORNO",'Revisión'!I2:I193,"Sí") | D19: =COUNTIFS('Revisión'!C2:C193,"ENTORNO",'Revisión'!I2:I193,"No") | E19: =COUNTIFS('Revisión'!C2:C193,"ENTORNO",'Revisión'!I2:I193,"Ambiguo")
A20: ESTRATEGIA | B20: =COUNTIF('Revisión'!C2:C193,"ESTRATEGIA") | C20: =COUNTIFS('Revisión'!C2:C193,"ESTRATEGIA",'Revisión'!I2:I193,"Sí") | D20: =COUNTIFS('Revisión'!C2:C193,"ESTRATEGIA",'Revisión'!I2:I193,"No") | E20: =COUNTIFS('Revisión'!C2:C193,"ESTRATEGIA",'Revisión'!I2:I193,"Ambiguo")
A23: Realista por tipo de respuesta | B23: Respuestas | C23: Sí | D23: No | E23: Ambiguo
A24: Equilibrada | B24: =COUNTIF('Revisión'!H2:H193,"Equilibrada") | C24: =COUNTIFS('Revisión'!H2:H193,"Equilibrada",'Revisión'!I2:I193,"Sí") | D24: =COUNTIFS('Revisión'!H2:H193,"Equilibrada",'Revisión'!I2:I193,"No") | E24: =COUNTIFS('Revisión'!H2:H193,"Equilibrada",'Revisión'!I2:I193,"Ambiguo")
A25: Atajo | B25: =COUNTIF('Revisión'!H2:H193,"Atajo") | C25: =COUNTIFS('Revisión'!H2:H193,"Atajo",'Revisión'!I2:I193,"Sí") | D25: =COUNTIFS('Revisión'!H2:H193,"Atajo",'Revisión'!I2:I193,"No") | E25: =COUNTIFS('Revisión'!H2:H193,"Atajo",'Revisión'!I2:I193,"Ambiguo")
A26: Ceder | B26: =COUNTIF('Revisión'!H2:H193,"Ceder") | C26: =COUNTIFS('Revisión'!H2:H193,"Ceder",'Revisión'!I2:I193,"Sí") | D26: =COUNTIFS('Revisión'!H2:H193,"Ceder",'Revisión'!I2:I193,"No") | E26: =COUNTIFS('Revisión'!H2:H193,"Ceder",'Revisión'!I2:I193,"Ambiguo")
A27: Pasiva | B27: =COUNTIF('Revisión'!H2:H193,"Pasiva") | C27: =COUNTIFS('Revisión'!H2:H193,"Pasiva",'Revisión'!I2:I193,"Sí") | D27: =COUNTIFS('Revisión'!H2:H193,"Pasiva",'Revisión'!I2:I193,"No") | E27: =COUNTIFS('Revisión'!H2:H193,"Pasiva",'Revisión'!I2:I193,"Ambiguo")
